pyfemtet_opt_gui/__init__.py
pyfemtet_opt_gui/__main__.py
pyfemtet_opt_gui/app_en_us.ts
pyfemtet_opt_gui/assets/icon/arrow.svg
pyfemtet_opt_gui/assets/samples/cad_ex01_SW.SLDPRT
pyfemtet_opt_gui/assets/samples/cad_ex01_SW.femprj
pyfemtet_opt_gui/assets/samples/sample.femprj
pyfemtet_opt_gui/builder/__init__.py
pyfemtet_opt_gui/builder/builder.py
pyfemtet_opt_gui/builder/file_dialog.py
pyfemtet_opt_gui/builder/main.py
pyfemtet_opt_gui/builder/worker.py
pyfemtet_opt_gui/common/__init__.py
pyfemtet_opt_gui/common/expression_processor.py
pyfemtet_opt_gui/common/pyfemtet_model_bases.py
pyfemtet_opt_gui/common/qt_util.py
pyfemtet_opt_gui/common/return_msg.py
pyfemtet_opt_gui/common/subtitle.html
pyfemtet_opt_gui/common/titles.py
pyfemtet_opt_gui/common/type_alias.py
pyfemtet_opt_gui/fem_interfaces/__init__.py
pyfemtet_opt_gui/fem_interfaces/base_fem_interface.py
pyfemtet_opt_gui/fem_interfaces/connection_worker.py
pyfemtet_opt_gui/fem_interfaces/femtet_interface/__init__.py
pyfemtet_opt_gui/fem_interfaces/femtet_interface/femtet_expression_support.py
pyfemtet_opt_gui/fem_interfaces/femtet_interface/femtet_interface.py
pyfemtet_opt_gui/fem_interfaces/mock.py
pyfemtet_opt_gui/fem_interfaces/solidworks_interface/__init__.py
pyfemtet_opt_gui/fem_interfaces/solidworks_interface/solidworks_expression_support.py
pyfemtet_opt_gui/fem_interfaces/solidworks_interface/solidworks_interface.py
pyfemtet_opt_gui/logger/__init__.py
pyfemtet_opt_gui/main.py
pyfemtet_opt_gui/models/__init__.py
pyfemtet_opt_gui/models/analysis_model/__init__.py
pyfemtet_opt_gui/models/analysis_model/analysis_model.py
pyfemtet_opt_gui/models/config/__init__.py
pyfemtet_opt_gui/models/config/algorithm/__init__.py
pyfemtet_opt_gui/models/config/algorithm/algorithm_nsga2.py
pyfemtet_opt_gui/models/config/algorithm/algorithm_pof_botorch.py
pyfemtet_opt_gui/models/config/algorithm/algorithm_random.py
pyfemtet_opt_gui/models/config/algorithm/algorithm_tpe.py
pyfemtet_opt_gui/models/config/algorithm/base.py
pyfemtet_opt_gui-0.10.6.dist-info/METADATA
pyfemtet_opt_gui-0.10.6.dist-info/WHEEL
pyfemtet_opt_gui-0.10.6.dist-info/entry_points.txt
pyfemtet_opt_gui-0.10.6.dist-info/licenses/LICENSE
pyfemtet_opt_gui-0.10.6.dist-info/RECORD
