Metadata-Version: 2.4
Name: pyfemtet-opt-gui
Version: 0.10.6
Summary: GUI to build and run a script for pyfemtet.opt
License-Expression: LGPL-3.0
License-File: LICENSE
Author: pyfemtet
Author-email: 148934231+pyfemtet@users.noreply.github.com
Requires-Python: >=3.11, <3.15
Classifier: Programming Language :: Python :: 3
Classifier: Programming Language :: Python :: 3.11
Classifier: Programming Language :: Python :: 3.12
Classifier: Programming Language :: Python :: 3.13
Classifier: Programming Language :: Python :: 3.14
Requires-Dist: pyfemtet (>=1.3.3,<2.0.0)
Requires-Dist: pyside6 (>=6.7.1,<7.0.0)
Project-URL: Repository, https://github.com/pyfemtet/pyfemtet-opt-gui
